<?xml version="1.0" encoding="UTF-8"?><record_update table="sys_properties">
    <sys_properties action="DELETE">
        <choices/>
        <description>The maximum amount of time to wait for an email event to process, in milliseconds.</description>
        <ignore_cache>true</ignore_cache>
        <is_private>false</is_private>
        <name>x_clgp_mail_to_acc.email_processing.max_wait</name>
        <read_roles/>
        <suffix>email_processing.max_wait</suffix>
        <sys_class_name>sys_properties</sys_class_name>
        <sys_created_by>Chris.Crockett@CloudGoServices.com</sys_created_by>
        <sys_created_on>2021-10-28 20:00:25</sys_created_on>
        <sys_id>702725601b2bb010749f0dc5604bcb56</sys_id>
        <sys_mod_count>1</sys_mod_count>
        <sys_name>x_clgp_mail_to_acc.email_processing.max_wait</sys_name>
        <sys_package display_value="Email-based Account Assignment for CSM" source="x_clgp_mail_to_acc">136aa4d01bebb4101738a932604bcb5d</sys_package>
        <sys_policy/>
        <sys_scope display_value="Email-based Account Assignment for CSM">136aa4d01bebb4101738a932604bcb5d</sys_scope>
        <sys_update_name>sys_properties_702725601b2bb010749f0dc5604bcb56</sys_update_name>
        <sys_updated_by>Chris.Crockett@CloudGoServices.com</sys_updated_by>
        <sys_updated_on>2021-10-28 20:00:42</sys_updated_on>
        <type>integer</type>
        <value>5000</value>
        <write_roles/>
    </sys_properties>
    <sys_translated_text action="DELETE" query="documentkey=702725601b2bb010749f0dc5604bcb56"/>
    <sys_update_version action="INSERT_OR_UPDATE">
        <action>DELETE</action>
        <application display_value="Email-based Account Assignment for CSM">136aa4d01bebb4101738a932604bcb5d</application>
        <file_path/>
        <instance_id>c0da2877db3eec102f68c597059619f7</instance_id>
        <instance_name>ven04370</instance_name>
        <name>sys_properties_702725601b2bb010749f0dc5604bcb56</name>
        <payload><![CDATA[<?xml version="1.0" encoding="UTF-8"?><record_update table="sys_properties"><sys_properties action="INSERT_OR_UPDATE"><choices/><description>The maximum amount of time to wait for an email event to process, in milliseconds.</description><ignore_cache>true</ignore_cache><is_private>false</is_private><name>x_clgp_mail_to_acc.email_processing.max_wait</name><read_roles/><suffix>email_processing.max_wait</suffix><sys_class_name>sys_properties</sys_class_name><sys_created_by>Chris.Crockett@CloudGoServices.com</sys_created_by><sys_created_on>2021-10-28 20:00:25</sys_created_on><sys_id>702725601b2bb010749f0dc5604bcb56</sys_id><sys_mod_count>1</sys_mod_count><sys_name>x_clgp_mail_to_acc.email_processing.max_wait</sys_name><sys_package display_value="Email-based Account Assignment for CSM" source="x_clgp_mail_to_acc">136aa4d01bebb4101738a932604bcb5d</sys_package><sys_policy/><sys_scope display_value="Email-based Account Assignment for CSM">136aa4d01bebb4101738a932604bcb5d</sys_scope><sys_update_name>sys_properties_702725601b2bb010749f0dc5604bcb56</sys_update_name><sys_updated_by>Chris.Crockett@CloudGoServices.com</sys_updated_by><sys_updated_on>2021-10-28 20:00:42</sys_updated_on><type>integer</type><value>5000</value><write_roles/></sys_properties><sys_translated_text action="delete_multiple" query="documentkey=702725601b2bb010749f0dc5604bcb56"/></record_update>]]></payload>
        <payload_hash>1803788319</payload_hash>
        <record_name>x_clgp_mail_to_acc.email_processing.max_wait</record_name>
        <reverted_from/>
        <source>136aa4d01bebb4101738a932604bcb60</source>
        <source_table>sys_update_set</source_table>
        <state>previous</state>
        <sys_created_by>Chris.Crockett@CloudGoServices.com</sys_created_by>
        <sys_created_on>2021-10-28 20:00:42</sys_created_on>
        <sys_id>8277a5601b2bb010749f0dc5604bcb4c</sys_id>
        <sys_mod_count>0</sys_mod_count>
        <sys_recorded_at>17cc87d89e00000001</sys_recorded_at>
        <sys_updated_by>Chris.Crockett@CloudGoServices.com</sys_updated_by>
        <sys_updated_on>2021-10-28 20:00:42</sys_updated_on>
        <type>System Property</type>
        <update_guid>ca77a560f22bb010117e37e043dac14b</update_guid>
        <update_guid_history>ca77a560f22bb010117e37e043dac14b:1803788319,bd6725a07b2bb010012749b2e785de7c:815880304</update_guid_history>
    </sys_update_version>
    <sys_metadata_delete action="INSERT_OR_UPDATE">
        <sys_audit_delete/>
        <sys_class_name>sys_metadata_delete</sys_class_name>
        <sys_created_by>Chris.Crockett@CloudGoServices.com</sys_created_by>
        <sys_created_on>2021-10-29 17:55:04</sys_created_on>
        <sys_db_object display_value="" name="sys_properties">sys_properties</sys_db_object>
        <sys_id>5e65de193e014bf6b40e124776374584</sys_id>
        <sys_metadata>702725601b2bb010749f0dc5604bcb56</sys_metadata>
        <sys_mod_count>0</sys_mod_count>
        <sys_name>x_clgp_mail_to_acc.email_processing.max_wait</sys_name>
        <sys_package display_value="Email-based Account Assignment for CSM" source="x_clgp_mail_to_acc">136aa4d01bebb4101738a932604bcb5d</sys_package>
        <sys_parent/>
        <sys_policy/>
        <sys_scope display_value="Email-based Account Assignment for CSM">136aa4d01bebb4101738a932604bcb5d</sys_scope>
        <sys_scope_delete display_value="">a119ec4638234ae4af8627a6fa2375e9</sys_scope_delete>
        <sys_update_name>sys_properties_702725601b2bb010749f0dc5604bcb56</sys_update_name>
        <sys_update_version display_value="sys_properties_702725601b2bb010749f0dc5604bcb56">8277a5601b2bb010749f0dc5604bcb4c</sys_update_version>
        <sys_updated_by>Chris.Crockett@CloudGoServices.com</sys_updated_by>
        <sys_updated_on>2021-10-29 17:55:04</sys_updated_on>
    </sys_metadata_delete>
</record_update>
